Workbook

Sheet DESCUENTOS MENSUALES
A1: BOPELUAL S.A. – CONTROL DE DESCUENTOS DE PERSONAL
A2: MES: JUNIO AÑO: 2026
A3: ▶ Llena solo las celdas blancas. Los totales se calculan automáticamente. Coloca 'cuota X/Y' en la columna DETALLE cuando aplique.
A4: N° | B4: EMPLEADO | C4: MEC | E4: SALUDSA | F4: PREVIEX | G4: RETENCIÓN TRIBUTARIAS | H4: PRÉSTAMOS INSTITUCIONALES | N4: ANTICIPO DE SUELDO | P4: EQUIPO CELULAR / TECNOLÓGICO | U4: OTROS (Multas / Atrasos / Sanciones) | X4: TOTAL DESCUENTOS
C5: MONTO $ | D5: DETALLE | H5: COMPAÑÍA | I5: MONTO $ | J5: SALDO DE DEUDA | K5: PLAZO | L5: CUOTA | M5: DETALLE | N5: MONTO $ | O5: DETALLE | P5: DESCRIPCIÓN | Q5: MONTO $ | R5: SALDO PENDIENTE | S5: PLAZO | T5: CUOTA | V5: MONTO $ | W5: DIAS
A6: ← EJEMPLO → Ingresa el nombre del empleado, monto y detalle en cada categoría que corresponda. El TOTAL se calculará solo.
A7: 1 | B7: MIGUEL TORAL | C7: 4 | D7: MEC JUNIO | E7: 0 | F7: 0 | G7: 0 | H7: BOPELUAL | I7: 350 | J7: 350 | K7: 3 MESES | L7: 3/3 | M7: PRESTAMO JUNIO SE DESCONTARA A PARTIR DESDE JULIO | X7: =IFERROR(SUM(C7,E7,F7,G7,I7,N7,Q7,V7),0) -> 354
A8: 2 | B8: DIANA CARRERA | C8: 60 | H8: BOPELUAL | I8: 800 | J8: 0 | K8: 3 MESES | L8: 3/3 | M8: DESCONTADO EN TOTALIDAD | X8: =IFERROR(SUM(C8,E8,F8,G8,I8,N8,Q8,V8),0) -> 860
A9: 3 | B9: CYNTHIA HIDALGO | C9: 4 | G9: 164 | H9: BOPELUAL | I9: 1839.96 | J9: 1073.31 | K9: 12 MESES | L9: 5/12 | M9: PRESTAMO DIC 2025 | X9: =IFERROR(SUM(C9,E9,F9,G9,I9,N9,Q9,V9),0) -> 2007.96
A10: 4 | B10: ANDRES NADER | C10: 4 | H10: BOPELUAL | I10: 600 | J10: 0 | K10: 6 MESES | L10: 6/6 | M10: DESCONTADO EN TOTALIDAD EN JUNIO | X10: =IFERROR(SUM(C10,E10,F10,G10,I10,N10,Q10,V10),0) -> 604
A11: 5 | B11: ALEJANDRO BOLOÑA | C11: 12 | H11: BOPELUAL | I11: 2000 | J11: 666.67 | K11: 3 MESES | L11: 2/3 | M11: PRESTAMO MARZO 2026 PIDIO PRORROGA PARA QUE SE DESC EN AGOSTO | X11: =IFERROR(SUM(C11,E11,F11,G11,I11,N11,Q11,V11),0) -> 2012
A12: 6 | B12: JORDI CRUZ | C12: 0 | H12: BOPELUAL | I12: 300 | J12: 0 | K12: 3 MESES | L12: 3/3 | M12: DECONTADO EN SU TOTALIDAD JUNIO | X12: =IFERROR(SUM(C12,E12,F12,G12,I12,N12,Q12,V12),0) -> 300
A13: 7 | B13: NUBIA ERAZO | C13: 0 | H13: BOPELUAL | P13: PERDIDA DE LAPTOP | Q13: 66.66 | R13: 22.22 | S13: 3 | T13: 3/3 | X13: =IFERROR(SUM(C13,E13,F13,G13,I13,N13,Q13,V13),0) -> 66.66
A14: 8 | B14: ALEJANDRO BOLOÑA | C14: 0 | H14: BOPELUAL | I14: 300 | J14: 0 | K14: 3 MESES | L14: 3/3 | M14: DECONTADO EN SU TOTALIDAD JUNIO | X14: =IFERROR(SUM(C14,E14,F14,G14,I14,N14,Q14,V14),0) -> 300
A15: 9 | B15: ELENA VILLAVICENCIO | C15: 0 | H15: BOPELUAL | I15: 200 | J15: 0 | K15: 2 MESES | L15: 2/2 | M15: DECONTADO EN SU TOTALIDAD JUNIO | X15: =IFERROR(SUM(C15,E15,F15,G15,I15,N15,Q15,V15),0) -> 200
A16: 11 | B16: LIDER INTRIAGO | C16: 4 | H16: CARROS YA | U16: PENSION ALIMENTICIA | V16: 142.14 | W16: CADA MES | X16: =IFERROR(SUM(C16,E16,F16,G16,I16,N16,Q16,V16),0) -> 146.14
A17: 12 | B17: JENNIFFER AVILES | C17: 4 | H17: CARROS YA | I17: 300 | J17: 300 | K17: 3 MESES | M17: DESCONTAR DESDE JULIO | X17: =IFERROR(SUM(C17,E17,F17,G17,I17,N17,Q17,V17),0) -> 304
A18: 13 | B18: GIANELLA BAUX | C18: 12 | E18: 47.71 | H18: CARROS YA | X18: =IFERROR(SUM(C18,E18,F18,G18,I18,N18,Q18,V18),0) -> 59.71
A19: 14 | B19: JHONAS LOPEZ | C19: 0 | E19: 93.08 | H19: BOPELUAL | X19: =IFERROR(SUM(C19,E19,F19,G19,I19,N19,Q19,V19),0) -> 93.08
A20: 15 | B20: ANDRES NADER | C20: 4 | E20: 28.68 | F20: 16.7 | H20: CARROS YA | X20: =IFERROR(SUM(C20,E20,F20,G20,I20,N20,Q20,V20),0) -> 49.38
A21: 16 | B21: JORGE LUCERO | C21: 20 | H21: BOPELUAL | U21: LENTES | V21: 22.22 | X21: =IFERROR(SUM(C21,E21,F21,G21,I21,N21,Q21,V21),0) -> 42.22
A22: 17 | B22: CHRISTIAN RODRIGUEZ | H22: BOPELUAL | I22: 200 | J22: 0 | K22: 1 | M22: DESCONTADO EN JUNIO | X22: =IFERROR(SUM(C22,E22,F22,G22,I22,N22,Q22,V22),0) -> 200
A23: 18 | X23: =IFERROR(SUM(C23,E23,F23,G23,I23,N23,Q23,V23),0) -> 0
A24: 19 | X24: =IFERROR(SUM(C24,E24,F24,G24,I24,N24,Q24,V24),0) -> 0
A25: 20 | X25: =IFERROR(SUM(C25,E25,F25,G25,I25,N25,Q25,V25),0) -> 0
A26: 21 | X26: =IFERROR(SUM(C26,E26,F26,G26,I26,N26,Q26,V26),0) -> 0
A27: 22 | X27: =IFERROR(SUM(C27,E27,F27,G27,I27,N27,Q27,V27),0) -> 0
A28: 23 | X28: =IFERROR(SUM(C28,E28,F28,G28,I28,N28,Q28,V28),0) -> 0
A29: 24 | X29: =IFERROR(SUM(C29,E29,F29,G29,I29,N29,Q29,V29),0) -> 0
A30: 25 | X30: =IFERROR(SUM(C30,E30,F30,G30,I30,N30,Q30,V30),0) -> 0
A31: 26 | X31: =IFERROR(SUM(C31,E31,F31,G31,I31,N31,Q31,V31),0) -> 0
A32: 27 | X32: =IFERROR(SUM(C32,E32,F32,G32,I32,N32,Q32,V32),0) -> 0
A33: 28 | X33: =IFERROR(SUM(C33,E33,F33,G33,I33,N33,Q33,V33),0) -> 0
A34: 29 | X34: =IFERROR(SUM(C34,E34,F34,G34,I34,N34,Q34,V34),0) -> 0
... A45: 40 | X45: =IFERROR(SUM(C45,E45,F45,G45,I45,N45,Q45,V45),0) -> 0
A46: TOTALES DEL MES | C46: =SUM(C7:C45) -> 128 | E46: =SUM(E7:E45) -> 169.47 | F46: =SUM(F7:F45) -> 16.7 | G46: =SUM(G7:G45) -> 164 | I46: =SUM(I7:I45) -> 6889.96 | N46: =SUM(N7:N45) -> 0 | Q46: =SUM(Q7:Q45) -> 66.66 | V46: =SUM(V7:V45) -> 164.36 | X46: =SUM(X7:X45) -> 7599.15

Sheet RESUMEN EJECUTIVO
A1: RESUMEN EJECUTIVO – DESCUENTOS DE NÓMINA - JUNIO
A2: Los valores se actualizan automáticamente desde la hoja DESCUENTOS MENSUALES
A3: CATEGORÍA | B3: TOTAL DESCONTADO $ | C3: N° EMPLEADOS AFECTADOS | D3: PROMEDIO POR EMPLEADO $ | E3: % DEL TOTAL
A4: MEC | B4: ='DESCUENTOS MENSUALES'!C46 -> 128 | C4: =COUNTIF('DESCUENTOS MENSUALES'!C7:C45,">0") -> 10 | D4: =IFERROR(B4/C4,0) -> 12.8 | E4: =IFERROR(B4/B12,0) -> 0.016843989
A5: SALUDSA | B5: ='DESCUENTOS MENSUALES'!E46 -> 169.47 | C5: =COUNTIF('DESCUENTOS MENSUALES'!E7:E45,">0") -> 3 | D5: =IFERROR(B5/C5,0) -> 56.49 | E5: =IFERROR(B5/B12,0) -> 0.022301178
A6: PREVIEX | B6: ='DESCUENTOS MENSUALES'!F46 -> 16.7 | C6: =COUNTIF('DESCUENTOS MENSUALES'!F7:F45,">0") -> 1 | D6: =IFERROR(B6/C6,0) -> 16.7 | E6: =IFERROR(B6/B12,0) -> 0.0021976142
A7: RETENCIÓN MES | B7: ='DESCUENTOS MENSUALES'!G46 -> 164 | C7: =COUNTIF('DESCUENTOS MENSUALES'!G7:G45,">0") -> 1 | D7: =IFERROR(B7/C7,0) -> 164 | E7: =IFERROR(B7/B12,0) -> 0.021581361
A8: PRÉSTAMOS | B8: ='DESCUENTOS MENSUALES'!I46 -> 6889.96 | C8: =COUNTIF('DESCUENTOS MENSUALES'!I7:I45,">0") -> 10 | D8: =IFERROR(B8/C8,0) -> 688.996 | E8: =IFERROR(B8/B12,0) -> 0.90667509
A9: ANTICIPO SUELDO | B9: ='DESCUENTOS MENSUALES'!N46 -> 0 | C9: =COUNTIF('DESCUENTOS MENSUALES'!N7:N45,">0") -> 0 | D9: =IFERROR(B9/C9,0) -> 0 | E9: =IFERROR(B9/B12,0) -> 0
A10: EQUIPO CELULAR / TECNOLÓGICO | B10: ='DESCUENTOS MENSUALES'!Q46 -> 66.66 | C10: =COUNTIF('DESCUENTOS MENSUALES'!Q7:Q45,">0") -> 1 | D10: =IFERROR(B10/C10,0) -> 66.66 | E10: =IFERROR(B10/B12,0) -> 0.0087720337
A11: OTROS (Multas / Atrasos / Sanciones) | B11: ='DESCUENTOS MENSUALES'!V46 -> 164.36 | C11: =COUNTIF('DESCUENTOS MENSUALES'!V7:V45,">0") -> 2 | D11: =IFERROR(B11/C11,0) -> 82.18 | E11: =IFERROR(B11/B12,0) -> 0.021628735
A12: GRAN TOTAL | B12: ='DESCUENTOS MENSUALES'!X46 -> 7599.15 | C12: =COUNTIF('DESCUENTOS MENSUALES'!P7:P45,">0") -> 0 | D12: =IFERROR(B12/C12,0) -> 0 | E12: =SUM(E4:E11) -> 1

Sheet INSTRUCCIONES
A1: INSTRUCCIONES DE USO
A2: 1 | B2: EMPLEADO | C2: Escribe el nombre completo del empleado en la columna B (celda amarilla).
A3: 2 | B3: MEC | C3: Ingresa el monto mensual descontado. En CUOTA escribe ej. '2/6'. En SALDO el saldo pendiente. DETALLE para observaciones.
A4: 3 | B4: SALUDSA | C4: Ingresa el valor mensual de descuento del seguro de salud.
A5: 4 | B5: PREVIEX | C5: Ingresa el valor mensual del plan de cesantía o jubilación privada.
A6: 5 | B6: RETENCIÓN MES | C6: Ingresa el valor de retención en la fuente aplicado en la quincena/fin de mes.
A7: 6 | B7: PRÉSTAMOS | C7: Registra el nombre de la entidad financiera, el monto de la cuota mensual y el detalle de cuota (ej. 'cuota 3/3').
A8: 7 | B8: ANTICIPO SUELDO | C8: Registra el anticipo entregado, la cuota que se descuenta, el saldo pendiente y cualquier observación (ej. 'descontar solo $128').
A9: 8 | B9: TOTAL | C9: La columna TOTAL DESCUENTOS (R) se calcula automáticamente. No editar.
A10: 8 | B10: EQUIPO CELULAR | C10: Ingresa la descripción del equipo (ej. 'iPhone 14 Pro'), el monto de la cuota mensual y el número de cuota (ej. '3/12'). Aplica para celulares, tablets, laptops u otros equipos tecnológicos financiados por la empresa.
A11: 9 | B11: OTROS | C11: Registra multas, descuentos por atrasos, sanciones comerciales u otros. Indica el MOTIVO (ej. 'Tardanza 3 días'), el MONTO a descontar y la FECHA del evento o resolución. El monto se suma automáticamente al TOTAL.
A12: 9 | B12: RESUMEN | C12: La hoja RESUMEN EJECUTIVO consolida los totales automáticamente para enviar a gerencia.
A13: 10 | B13: COMPARTIR | C13: Guarda el archivo en Google Drive y comparte con Alexandra, Fabiola y Gisell con permisos de edición.
